ccltt/__about__.py
ccltt/__init__.py
ccltt/ccl_manager.py
ccltt/ccl_tt_node.py
ccltt/ccl_tt_tree.py
ccltt/data_base.py
ccltt/tt.txt
ccltt-0.0.16.dist-info/METADATA
ccltt-0.0.16.dist-info/WHEEL
ccltt-0.0.16.dist-info/RECORD
