Metadata-Version: 2.4
Name: ccltt
Version: 0.0.16
Project-URL: Documentation, https://github.com/Flyshde/ccltt#readme
Project-URL: Issues, https://github.com/Flyshde/ccltt/issues
Project-URL: Source, https://github.com/Flyshde/ccltt
Author-email: Flyshde <zhangyang@outlook.es>
License: MIT
Classifier: Development Status :: 4 - Beta
Classifier: Programming Language :: Python
Classifier: Programming Language :: Python :: 3.8
Classifier: Programming Language :: Python :: 3.9
Classifier: Programming Language :: Python :: 3.10
Classifier: Programming Language :: Python :: 3.11
Classifier: Programming Language :: Python :: 3.12
Classifier: Programming Language :: Python :: Implementation :: CPython
Classifier: Programming Language :: Python :: Implementation :: PyPy
Requires-Python: >=3.8
